redis_sdk/__init__.py
redis_sdk/asyncio/__init__.py
redis_sdk/asyncio/client.py
redis_sdk/client.py
redis_sdk/commands.py
redis_sdk/commands.pyi
redis_sdk/errors.py
redis_sdk/format.py
redis_sdk/http.py
redis_sdk/py.typed
redis_sdk/typing.py
redis_sdk/utils.py
redis_sdk-1.0.0.dist-info/LICENSE
redis_sdk-1.0.0.dist-info/METADATA
redis_sdk-1.0.0.dist-info/WHEEL
redis_sdk-1.0.0.dist-info/RECORD
