Metadata-Version: 2.1
Name: redis-sdk
Version: 1.0.0
Summary: Serverless Redis SDK from Khulnasoft
Home-page: https://github.com/khulnasoft-lab/redispy
License: MIT
Keywords: Khulnasoft Redis,Serverless Redis
Author: Khulnasoft
Author-email: support@khulnasoft.com
Maintainer: Khulnasoft
Maintainer-email: support@khulnasoft.com
Requires-Python: >=3.8,<4.0
Classifier: Development Status :: 5 - Production/Stable
Classifier: Intended Audience :: Developers
Classifier: License :: OSI Approved :: MIT License
Classifier: Operating System :: OS Independent
Classifier: Programming Language :: Python
Classifier: Programming Language :: Python :: 3
Classifier: Programming Language :: Python :: 3.8
Classifier: Programming Language :: Python :: 3.9
Classifier: Programming Language :: Python :: 3.10
Classifier: Programming Language :: Python :: 3.11
Classifier: Programming Language :: Python :: 3.12
Classifier: Programming Language :: Python :: 3 :: Only
Classifier: Programming Language :: Python :: Implementation :: CPython
Classifier: Topic :: Database
Classifier: Topic :: Database :: Front-Ends
Classifier: Topic :: Software Development :: Libraries
Requires-Dist: aiohttp (>=3.8.4,<4.0.0)
Requires-Dist: requests (>=2.31.0,<3.0.0)
Project-URL: Repository, https://github.com/khulnasoft-lab/redispy
